buildlog/__init__.py
buildlog/cli.py
buildlog/confidence.py
buildlog/distill.py
buildlog/embeddings.py
buildlog/llm.py
buildlog/seeds.py
buildlog/skills.py
buildlog/stats.py
buildlog/core/__init__.py
buildlog/core/bandit.py
buildlog/core/operations.py
buildlog/data/__init__.py
buildlog/data/seeds/security_karen.yaml
buildlog/data/seeds/test_terrorist.yaml
buildlog/engine/__init__.py
buildlog/engine/bandit.py
buildlog/engine/confidence.py
buildlog/engine/embeddings.py
buildlog/engine/experiments.py
buildlog/engine/types.py
buildlog/mcp/__init__.py
buildlog/mcp/server.py
buildlog/mcp/tools.py
buildlog/render/__init__.py
buildlog/render/base.py
buildlog/render/claude_md.py
buildlog/render/continue_dev.py
buildlog/render/copilot.py
buildlog/render/cursor.py
buildlog/render/settings_json.py
buildlog/render/skill.py
buildlog/render/tracking.py
buildlog/render/windsurf.py
buildlog/seed_engine/__init__.py
buildlog/seed_engine/categorizers.py
buildlog/seed_engine/extractors.py
buildlog/seed_engine/generators.py
buildlog/seed_engine/models.py
buildlog/seed_engine/pipeline.py
buildlog/seed_engine/sources.py
buildlog-0.8.0.data/data/share/buildlog/copier.yml
buildlog-0.8.0.data/data/share/buildlog/post_gen.py
buildlog-0.8.0.data/data/share/buildlog/template/buildlog/.gitkeep
buildlog-0.8.0.data/data/share/buildlog/template/buildlog/2026-01-01-example.md
buildlog-0.8.0.data/data/share/buildlog/template/buildlog/BUILDLOG_SYSTEM.md
buildlog-0.8.0.data/data/share/buildlog/template/buildlog/_TEMPLATE.md
buildlog-0.8.0.data/data/share/buildlog/template/buildlog/_TEMPLATE_QUICK.md
buildlog-0.8.0.data/data/share/buildlog/template/buildlog/assets/.gitkeep
buildlog-0.8.0.dist-info/METADATA
buildlog-0.8.0.dist-info/WHEEL
buildlog-0.8.0.dist-info/entry_points.txt
buildlog-0.8.0.dist-info/licenses/LICENSE
buildlog-0.8.0.dist-info/RECORD
