Metadata-Version: 2.4
Name: buildlog
Version: 0.8.0
Summary: Engineering notebook for AI-assisted development
Project-URL: Homepage, https://github.com/Peleke/buildlog-template
Project-URL: Repository, https://github.com/Peleke/buildlog-template
Author: Peleke Sengstacke
License-Expression: MIT
License-File: LICENSE
Keywords: ai,buildlog,development,documentation,journal
Classifier: Development Status :: 4 - Beta
Classifier: Environment :: Console
Classifier: Intended Audience :: Developers
Classifier: License :: OSI Approved :: MIT License
Classifier: Programming Language :: Python :: 3
Classifier: Programming Language :: Python :: 3.10
Classifier: Programming Language :: Python :: 3.11
Classifier: Programming Language :: Python :: 3.12
Classifier: Programming Language :: Python :: 3.13
Classifier: Topic :: Documentation
Classifier: Topic :: Software Development :: Documentation
Requires-Python: >=3.10
Requires-Dist: click>=8.0.0
Requires-Dist: copier>=9.0.0
Requires-Dist: numpy>=1.21.0
Requires-Dist: pymupdf>=1.26.7
Requires-Dist: pyyaml>=6.0.0
Provides-Extra: all
Requires-Dist: anthropic>=0.40.0; extra == 'all'
Requires-Dist: mcp>=1.0.0; extra == 'all'
Requires-Dist: ollama>=0.4.0; extra == 'all'
Requires-Dist: openai>=1.0.0; extra == 'all'
Requires-Dist: sentence-transformers>=2.2.0; extra == 'all'
Provides-Extra: anthropic
Requires-Dist: anthropic>=0.40.0; extra == 'anthropic'
Provides-Extra: dev
Requires-Dist: black>=24.0.0; extra == 'dev'
Requires-Dist: flake8>=7.0.0; extra == 'dev'
Requires-Dist: isort>=5.13.0; extra == 'dev'
Requires-Dist: mkdocs-material>=9.5.0; extra == 'dev'
Requires-Dist: mypy>=1.8.0; extra == 'dev'
Requires-Dist: pre-commit>=3.6.0; extra == 'dev'
Requires-Dist: pytest-asyncio>=0.21.0; extra == 'dev'
Requires-Dist: pytest-cov>=4.0.0; extra == 'dev'
Requires-Dist: pytest>=7.0.0; extra == 'dev'
Requires-Dist: types-pyyaml>=6.0.0; extra == 'dev'
Provides-Extra: embeddings
Requires-Dist: sentence-transformers>=2.2.0; extra == 'embeddings'
Provides-Extra: engine
Provides-Extra: llm
Requires-Dist: anthropic>=0.40.0; extra == 'llm'
Requires-Dist: ollama>=0.4.0; extra == 'llm'
Provides-Extra: mcp
Requires-Dist: mcp>=1.0.0; extra == 'mcp'
Provides-Extra: ollama
Requires-Dist: ollama>=0.4.0; extra == 'ollama'
Provides-Extra: openai
Requires-Dist: openai>=1.0.0; extra == 'openai'
